whitesymex/__init__.py
whitesymex/cli.py
whitesymex/errors.py
whitesymex/imp.py
whitesymex/instruction.py
whitesymex/ops.py
whitesymex/parameter.py
whitesymex/parser.py
whitesymex/path_group.py
whitesymex/solver.py
whitesymex/state.py
whitesymex/strategies/__init__.py
whitesymex/strategies/bfs.py
whitesymex/strategies/dfs.py
whitesymex/strategies/random.py
whitesymex/strategies/strategy.py
whitesymex-0.1.0.dist-info/LICENSE
whitesymex-0.1.0.dist-info/METADATA
whitesymex-0.1.0.dist-info/WHEEL
whitesymex-0.1.0.dist-info/entry_points.txt
whitesymex-0.1.0.dist-info/top_level.txt
whitesymex-0.1.0.dist-info/RECORD
