Metadata-Version: 2.1
Name: whitesymex
Version: 0.1.0
Summary: Symbolic execution engine for Whitespace language.
Home-page: https://github.com/umutoztunc/whitesymex
Author: Umut Barış Öztunç
Author-email: umutoztunc@gmail.com
License: MIT License
Platform: UNKNOWN
Classifier: Operating System :: OS Independent
Classifier: License :: OSI Approved :: MIT License
Classifier: Programming Language :: Python :: 3
Classifier: Programming Language :: Python :: 3.7
Classifier: Programming Language :: Python :: 3.8
Classifier: Programming Language :: Python :: 3.9
Requires-Python: >=3.7
License-File: LICENSE
Requires-Dist: z3-solver
